hyperpocket_anthropic/__init__.py
hyperpocket_anthropic/pocket_anthropic.py
hyperpocket_anthropic/util/__init__.py
hyperpocket_anthropic/util/tool_to_anthropic_spec.py
hyperpocket_anthropic-0.5.7.dist-info/METADATA
hyperpocket_anthropic-0.5.7.dist-info/WHEEL
hyperpocket_anthropic-0.5.7.dist-info/RECORD
